yb_enigma/__init__.py
yb_enigma/cli.py
yb_enigma/common.py
yb_enigma/enigma.py
yb_enigma/exceptions.py
yb_enigma/plugboard.py
yb_enigma/reflector.py
yb_enigma/rotor.py
yb_enigma/utils.py
yb_enigma-1.0.1.dist-info/METADATA
yb_enigma-1.0.1.dist-info/WHEEL
yb_enigma-1.0.1.dist-info/entry_points.txt
yb_enigma-1.0.1.dist-info/top_level.txt
yb_enigma-1.0.1.dist-info/RECORD
