Metadata-Version: 2.1
Name: yb-enigma
Version: 1.0.1
Summary: Simple Enigma machine emulator
Home-page: http://github.com/yuriybl/yb-enigma
Author: Yurii Bliusiuk
Author-email: ura.blusuk@gmail.com
License: MIT
Platform: UNKNOWN
